pallapay/__init__.py
pallapay/client.py
pallapay/enums.py
pallapay/request.py
pallapay/schema.py
pallapay/utils.py
pallapay_python_sdk-1.0.0.dist-info/LICENSE
pallapay_python_sdk-1.0.0.dist-info/METADATA
pallapay_python_sdk-1.0.0.dist-info/WHEEL
pallapay_python_sdk-1.0.0.dist-info/top_level.txt
pallapay_python_sdk-1.0.0.dist-info/RECORD
